imputer_apsus/__init__.py
imputer_apsus/imputer.py
imputer_apsus/src/analysis/__init__.py
imputer_apsus/src/analysis/metrics.py
imputer_apsus/src/features/__init__.py
imputer_apsus/src/features/encode.py
imputer_apsus/src/features/normalize.py
imputer_apsus/src/models/__init__.py
imputer_apsus/src/models/random_forest.py
imputer_apsus-0.0.2.dist-info/licenses/LICENSE
imputer_apsus-0.0.2.dist-info/METADATA
imputer_apsus-0.0.2.dist-info/WHEEL
imputer_apsus-0.0.2.dist-info/top_level.txt
imputer_apsus-0.0.2.dist-info/RECORD
