Metadata-Version: 2.4
Name: imputer_apsus
Version: 0.0.2
Summary: Data imputation library for APSUS healthcare datasets.
Author-email: Lucas Emanoel <lucas2014.barros@gmail.com>
Project-URL: Homepage, https://github.com/SmartAPSUS/analisededados
Project-URL: Issues, https://github.com/SmartAPSUS/analisededados/issues
Classifier: Programming Language :: Python :: 3
Classifier: License :: OSI Approved :: MIT License
Classifier: Operating System :: OS Independent
Requires-Python: >=3.10
License-File: LICENSE
Requires-Dist: scikit-learn>=1.0.0
Requires-Dist: pandas>=1.3.0
Requires-Dist: numpy>=1.21.0
Dynamic: license-file
